odoo/addons/auth_from_http_remote_user/README.rst
odoo/addons/auth_from_http_remote_user/__init__.py
odoo/addons/auth_from_http_remote_user/__manifest__.py
odoo/addons/auth_from_http_remote_user/utils.py
odoo/addons/auth_from_http_remote_user/controllers/__init__.py
odoo/addons/auth_from_http_remote_user/controllers/main.py
odoo/addons/auth_from_http_remote_user/i18n/am.po
odoo/addons/auth_from_http_remote_user/i18n/ar.po
odoo/addons/auth_from_http_remote_user/i18n/auth_from_http_remote_user.pot
odoo/addons/auth_from_http_remote_user/i18n/bg.po
odoo/addons/auth_from_http_remote_user/i18n/bs.po
odoo/addons/auth_from_http_remote_user/i18n/ca.po
odoo/addons/auth_from_http_remote_user/i18n/cs.po
odoo/addons/auth_from_http_remote_user/i18n/da.po
odoo/addons/auth_from_http_remote_user/i18n/de.po
odoo/addons/auth_from_http_remote_user/i18n/el_GR.po
odoo/addons/auth_from_http_remote_user/i18n/en_GB.po
odoo/addons/auth_from_http_remote_user/i18n/es.po
odoo/addons/auth_from_http_remote_user/i18n/es_AR.po
odoo/addons/auth_from_http_remote_user/i18n/es_CL.po
odoo/addons/auth_from_http_remote_user/i18n/es_CO.po
odoo/addons/auth_from_http_remote_user/i18n/es_CR.po
odoo/addons/auth_from_http_remote_user/i18n/es_DO.po
odoo/addons/auth_from_http_remote_user/i18n/es_EC.po
odoo/addons/auth_from_http_remote_user/i18n/es_ES.po
odoo/addons/auth_from_http_remote_user/i18n/es_MX.po
odoo/addons/auth_from_http_remote_user/i18n/es_PE.po
odoo/addons/auth_from_http_remote_user/i18n/es_PY.po
odoo/addons/auth_from_http_remote_user/i18n/es_VE.po
odoo/addons/auth_from_http_remote_user/i18n/et.po
odoo/addons/auth_from_http_remote_user/i18n/eu.po
odoo/addons/auth_from_http_remote_user/i18n/fa.po
odoo/addons/auth_from_http_remote_user/i18n/fi.po
odoo/addons/auth_from_http_remote_user/i18n/fr.po
odoo/addons/auth_from_http_remote_user/i18n/fr_CA.po
odoo/addons/auth_from_http_remote_user/i18n/fr_CH.po
odoo/addons/auth_from_http_remote_user/i18n/gl.po
odoo11_addon_auth_from_http_remote_user-11.0.1.0.0.99.dev6.dist-info/METADATA
odoo11_addon_auth_from_http_remote_user-11.0.1.0.0.99.dev6.dist-info/RECORD
odoo11_addon_auth_from_http_remote_user-11.0.1.0.0.99.dev6.dist-info/WHEEL
odoo11_addon_auth_from_http_remote_user-11.0.1.0.0.99.dev6.dist-info/top_level.txt
