Metadata-Version: 2.1
Name: odoo11-addon-auth-from-http-remote-user
Version: 11.0.1.0.0.99.dev6
Summary: Authenticate via HTTP Remote User
Home-page: https://github.com/OCA/server-auth
Author: Acsone SA/NV,Odoo Community Association (OCA)
Author-email: support@odoo-community.org
License: AGPL-3
Platform: UNKNOWN
Classifier: Programming Language :: Python
Classifier: Framework :: Odoo
Classifier: License :: OSI Approved :: GNU Affero General Public License v3
Requires-Python: >=2.7, !=3.0.*, !=3.1.*, !=3.2.*, !=3.3.*, !=3.4.*
Requires-Dist: odoo (<11.1dev,>=11.0a)
